Workbook

Sheet Dados Geral
C1: Quest.01 | D1: Quest.02 | E1: Quest.03 | F1: Quest.04 | G1: Quest.05 | H1: Quest.06 | I1: Quest.07 | J1: Quest.08 | K1: Quest.09 | L1: Quest.10 | M1: Quest.11 | N1: Quest.12 | O1: Quest.13 | P1: Quest.14 | Q1: Quest.15 | R1: Quest.16 | S1: Quest.17 | T1: Quest.18 | U1: Quest.19 | V1: Quest.20 | W1: Quest.21 | X1: Quest.22 | Y1: Quest.23 | Z1: Quest.24 | AA1: Quest.25 | AB1: Quest.26 | AC1: Quest.27 | AD1: Quest.28 | AE1: Quest.29 | AF1: Quest.30 | AG1: Quest.31 | AH1: Quest.32 | AI1: Quest.33 | AJ1: Quest.34 | AK1: Quest.35 | AL1: Quest.36 | AM1: Quest.37 | AN1: Quest.38 | AO1: Quest.39 | AP1: Quest.40 | AQ1: Quest.41 | AR1: Quest.42 | AS1: Quest.43 | AT1: Quest.44 | AU1: Quest.45 | AV1: Quest.46 | AW1: Quest.47 | AX1: Quest.48 | AY1: Quest.49 | AZ1: Quest.50 | BA1: Quest.51 | BB1: Quest.52 | BC1: Quest.53 | BD1: Quest.54 | BE1: Quest.55 | BF1: Quest.56 | BG1: Quest.57 | BH1: Quest.58 | BI1: Quest.59 | BJ1: Quest.60 | BK1: Quest.61 | BL1: Quest.62 | BM1: Quest.63 | BN1: Quest.64 | BO1: Quest.65 | BP1: Quest.66 | BQ1: Quest.67 | BR1: Quest.68 | BS1: Quest.69 | BT1: Quest.70 | BU1: Quest.71 | BV1: Quest.72 | BW1: Quest.73 | BX1: Quest.74 | BY1: Quest.75 | BZ1: Quest.76 | CA1: Quest.77 | CB1: Quest.78 | CC1: Quest.79 | CD1: Quest.80 | CE1: Quest.81 | CF1: Quest.82 | CG1: Frequencia
A2: Sigla | B2: FUNDAÇÃO | C2: Informa claramente sobre o seu ramo de atividade | D2: Indica inequivocamente quem são os beneficiários das suas operações | E2: A missão da organização está claramente definida | F2: A visão da organização está claramente definida | G2: Os valores estão enunciados e a interpretação que a organização faz deles são definidos | H2: Informações sobre os interesses que representa (da ciência e tecnologia, de ensino, pesquisa e extensão) | I2: Os objetivos da organização são claros, precisos e passíveis de avaliação | J2: Descrição dos projetos e programas desenvolvidos. | K2: Calendário de eventos | L2: Serviço de notícias | M2: Fornece informações precisas e quantitativas sobre o ambiente político da organização não governamental de desenvolvimento | N2: Informa sobre os processos de qualidade implementados pela organização | O2: Informa sobre o total de pessoas contratadas | P2: Informa sobre a existência do total de voluntários | Q2: Informações sobre o regime jurídico e tipo de contratos de trabalho do pessoal | R2: Indica a estrutura da organização | S2: Informações sobre treinamentos realizados pelo pessoal da organização | T2: Recursos educacionais (apresentação de slides, cursos, vídeos,) | U2: Informações sobre vínculos com financiadores, associações ou empresas | V2: Nomes e histórico sucinto de todos os membros dos conselhos diretivos e de administração | W2: Calendário de reuniões | X2: Estatutos, regulamentos ou regimes internos de funcionamento | Y2: Divulga os acordos adotados nas reuniões convocadas | Z2: Informa sobre os procedimentos de eleição e destituição de membros do conselho de administração curadores | AA2: Informa sobre a política de remuneração dos componentes do conselho diretivo e de administração | AB2: Eixo estratégico do orçamento | AC2: Orçamento distribuído por programas, projetos e convênios | AD2: Despesas orçamentárias por classe | AE2: Oferece resumos de dados financeiros | AF2: Slides e gráficos são incluídos como suporte à apresentação dos dados financeiros | AG2: Relatório anual (2022) - (gestão, atividades, planejamento estratégico e prestação de contas TCU) | AH2: Relatórios anuais de anos anteriores (mínimo 2 anos) 2021, 2020 | AI2: Balanço patrimonial do exercício atual | AJ2: Balanço patrimonial dos anos anteriores (mínimo 2 anos) | AK2: Demonstração do resultado do exercício atual | AL2: Demonstração do resultado dos anos anteriores (mínimo 2 anos) | AM2: Demonstração das Mutações do Patrimônio Líquido do exercício atual | AN2: Demonstração das Mutações do Patrimônio Líquido dos anos anteriores (mínimo 2 anos) | AO2: Notas explicativas do exercício atual | AP2: Notas explicativas dos anos anteriores (mínimo 2 anos) | AQ2: Demonstrativo de receitas e despesas | AR2: Demonstrativo de receitas e despesas de exercícios anteriores (mínimo 2 anos) | AS2: Origem e destinação dos recursos por projeto/programa e atividade | AT2: Rácio entre os custos de captação dos recursos e os custos totais da organização | AU2: Rácio entre os custos fixos e os custos totais da organização | AV2: Relatório de auditoria | AW2: Relatório de auditoria de anos anteriores (mínimo de 2 anos) | AX2: Apresenta as normas contábeis utilizadas | AY2: Relatório de avaliação dos projetos e programas, com comparativo entre metas propostas e resultados alcançados | AZ2: Identificação dos principais fornecedores e coorganizadores das atividades | BA2: Cópia dos contratos, termos e convênios firmados | BB2: Há uma área específica para governança e informações financeiras | BC2: Há uma área específica para informações gerais | BD2: Há links para outros sites relacionados | BE2: Um endereço de e-mail para contato é fornecido | BF2: O conteúdo é apresentado em um maneira estruturada e alinhada e pode ser acessado rápida e diretamente | BG2: Os títulos são claros e significativos e a linguagem utilizada é adaptada aos cidadãos | BH2: Divulgação de fotografias das atividades desenvolvidas pela organização | BI2: Divulgação de vídeos das atividades realizadas pela organização | BJ2: Existe um correio postal endereço, número de telefone e fax, etc. da pessoa de contato | BK2: Existe um sistema de busca | BL2: Existe um sistema de busca avançada | BM2: Um mapa do site da Web está incluído | BN2: Existe um menu de ajuda | BO2: Há informações em outros idiomas (pelo menos em inglês) | BP2: É permitido o download de arquivos em formato de planilha | BQ2: Existe um sistema de hiperlinks que relaciona diferentes áreas do site | BR2: São utilizados formatos que permitem a impressão correta da informação | BS2: A velocidade de resposta ao navegar no site que não impeça a efetiva qualidade da consulta | BT2: Existe uma área para perguntas frequentes | BU2: Estabelece normas de acessibilidade para pessoas com deficiência | BV2: Indica a data da última atualização | BW2: Pode-se ser notificado por e-mail quando atualizações são feitas | BX2: Indica quando as informações são criadas por terceiro | BY2: O site possui um espaço de uso exclusivo para facilitar a administração de pessoal e de atividades | BZ2: Publicam- se ofertas de trabalho ou editais de contratação para pessoal remunerado | CA2: Doações online podem ser feitas | CB2: São oferecidas parcerias ou adesões | CC2: São publicados boletins periódicos de informações sobre as atividades da organização | CD2: Existem fóruns abertos para envio de sugestões, críticas ou comentários sobre o trabalho desenvolvido pela organização | CE2: Os usuários têm a oportunidade de receber atualizações regulares por meio eletrônico | CF2: Os parceiros têm um espaço de acesso exclusivo que lhes permite realizar atividades administrativas: obter certificados de doações, atualizar seus dados, fazer contribuições, etc.
A3: AC | B3: FAPAC | C3: 0 | D3: 0 | E3: 0 | F3: 0 | G3: 0 | H3: 1 | I3: 0 | J3: 0 | K3: 0 | L3: 0 | M3: 0 | N3: 0 | O3: 0 | P3: 0 | Q3: 1 | R3: 0 | S3: 0 | T3: 1 | U3: 0 | V3: 0 | W3: 0 | X3: 0 | Y3: 0 | Z3: 0 | AA3: 1 | AB3: 0 | AC3: 0 | AD3: 0 | AE3: 0 | AF3: 0 | AG3: 0 | AH3: 0 | AI3: 0 | AJ3: 1 | AK3: 0 | AL3: 0 | AM3: 1 | AN3: 0 | AO3: 0 | AP3: 0 | AQ3: 0 | AR3: 0 | AS3: 0 | AT3: 1 | AU3: 0 | AV3: 0 | AW3: 0 | AX3: 0 | AY3: 0 | AZ3: 0 | BA3: 0 | BB3: 0 | BC3: 1 | BD3: 0 | BE3: 0 | BF3: 1 | BG3: 0 | BH3: 0 | BI3: 0 | BJ3: 0 | BK3: 1 | BL3: 0 | BM3: 1 | BN3: 0 | BO3: 1 | BP3: 1 | BQ3: 0 | BR3: 0 | BS3: 1 | BT3: 0 | BU3: 1 | BV3: 0 | BW3: 1 | BX3: 1 | BY3: 0 | BZ3: 0 | CA3: 1 | CB3: 0 | CC3: 0 | CD3: 0 | CE3: 1 | CF3: 0 | CG3: =SUM(C3:CF3)/82 -> 0.23170732
A4: AL | B4: PAFEAL | C4: 1 | D4: 1 | E4: 1 | F4: 1 | G4: 1 | H4: 0 | I4: 1 | J4: 1 | K4: 0 | L4: 1 | M4: 1 | N4: 1 | O4: 1 | P4: 0 | Q4: 1 | R4: 1 | S4: 0 | T4: 1 | U4: 1 | V4: 1 | W4: 1 | X4: 1 | Y4: 1 | Z4: 1 | AA4: 0 | AB4: 1 | AC4: 1 | AD4: 0 | AE4: 1 | AF4: 1 | AG4: 1 | AH4: 1 | AI4: 0 | AJ4: 1 | AK4: 1 | AL4: 0 | AM4: 1 | AN4: 1 | AO4: 1 | AP4: 1 | AQ4: 1 | AR4: 1 | AS4: 1 | AT4: 0 | AU4: 1 | AV4: 1 | AW4: 0 | AX4: 1 | AY4: 1 | AZ4: 1 | BA4: 1 | BB4: 0 | BC4: 1 | BD4: 1 | BE4: 0 | BF4: 1 | BG4: 1 | BH4: 0 | BI4: 1 | BJ4: 0 | BK4: 1 | BL4: 0 | BM4: 1 | BN4: 1 | BO4: 0 | BP4: 1 | BQ4: 0 | BR4: 0 | BS4: 1 | BT4: 0 | BU4: 1 | BV4: 1 | BW4: 0 | BX4: 1 | BY4: 0 | BZ4: 0 | CA4: 0 | CB4: 0 | CC4: 0 | CD4: 0 | CE4: 0 | CF4: 1 | CG4: =SUM(C4:CF4)/82 -> 0.67073171
A5: AP | B5: FAPEAP | C5: 0 | D5: 0 | E5: 0 | F5: 0 | G5: 0 | H5: 0 | I5: 0 | J5: 1 | K5: 1 | L5: 0 | M5: 1 | N5: 1 | O5: 1 | P5: 0 | Q5: 0 | R5: 0 | S5: 0 | T5: 0 | U5: 0 | V5: 0 | W5: 0 | X5: 0 | Y5: 0 | Z5: 0 | AA5: 0 | AB5: 0 | AC5: 1 | AD5: 1 | AE5: 0 | AF5: 1 | AG5: 1 | AH5: 1 | AI5: 0 | AJ5: 0 | AK5: 0 | AL5: 0 | AM5: 0 | AN5: 0 | AO5: 0 | AP5: 0 | AQ5: 0 | AR5: 0 | AS5: 0 | AT5: 0 | AU5: 0 | AV5: 1 | AW5: 1 | AX5: 0 | AY5: 1 | AZ5: 1 | BA5: 1 | BB5: 0 | BC5: 0 | BD5: 0 | BE5: 0 | BF5: 0 | BG5: 0 | BH5: 1 | BI5: 0 | BJ5: 0 | BK5: 1 | BL5: 1 | BM5: 0 | BN5: 0 | BO5: 1 | BP5: 1 | BQ5: 1 | BR5: 0 | BS5: 1 | BT5: 1 | BU5: 0 | BV5: 0 | BW5: 1 | BX5: 1 | BY5: 1 | BZ5: 1 | CA5: 0 | CB5: 1 | CC5: 0 | CD5: 1 | CE5: 0 | CF5: 0 | CG5: =SUM(C5:CF5)/82 -> 0.35365854
A6: AM | B6: FAPEAM | C6: 0 | D6: 0 | E6: 0 | F6: 0 | G6: 0 | H6: 1 | I6: 0 | J6: 0 | K6: 0 | L6: 0 | M6: 0 | N6: 0 | O6: 1 | P6: 0 | Q6: 0 | R6: 0 | S6: 0 | T6: 0 | U6: 0 | V6: 0 | W6: 0 | X6: 0 | Y6: 0 | Z6: 0 | AA6: 1 | AB6: 0 | AC6: 0 | AD6: 0 | AE6: 0 | AF6: 0 | AG6: 0 | AH6: 1 | AI6: 0 | AJ6: 0 | AK6: 0 | AL6: 0 | AM6: 0 | AN6: 0 | AO6: 0 | AP6: 0 | AQ6: 0 | AR6: 0 | AS6: 0 | AT6: 1 | AU6: 0 | AV6: 0 | AW6: 0 | AX6: 0 | AY6: 0 | AZ6: 0 | BA6: 1 | BB6: 0 | BC6: 0 | BD6: 0 | BE6: 0 | BF6: 0 | BG6: 0 | BH6: 1 | BI6: 1 | BJ6: 1 | BK6: 0 | BL6: 0 | BM6: 1 | BN6: 1 | BO6: 1 | BP6: 1 | BQ6: 1 | BR6: 1 | BS6: 0 | BT6: 0 | BU6: 1 | BV6: 1 | BW6: 1 | BX6: 1 | BY6: 1 | BZ6: 0 | CA6: 0 | CB6: 0 | CC6: 0 | CD6: 0 | CE6: 1 | CF6: 0 | CG6: =SUM(C6:CF6)/82 -> 0.25609756
A7: BA | B7: FAPESB | C7: 1 | D7: 1 | E7: 1 | F7: 1 | G7: 1 | H7: 0 | I7: 1 | J7: 0 | K7: 0 | L7: 1 | M7: 0 | N7: 0 | O7: 0 | P7: 0 | Q7: 1 | R7: 1 | S7: 1 | T7: 0 | U7: 1 | V7: 1 | W7: 1 | X7: 1 | Y7: 1 | Z7: 1 | AA7: 0 | AB7: 1 | AC7: 0 | AD7: 0 | AE7: 1 | AF7: 0 | AG7: 0 | AH7: 0 | AI7: 0 | AJ7: 1 | AK7: 1 | AL7: 1 | AM7: 0 | AN7: 1 | AO7: 1 | AP7: 1 | AQ7: 1 | AR7: 1 | AS7: 1 | AT7: 0 | AU7: 1 | AV7: 0 | AW7: 0 | AX7: 1 | AY7: 0 | AZ7: 0 | BA7: 0 | BB7: 0 | BC7: 1 | BD7: 1 | BE7: 1 | BF7: 0 | BG7: 1 | BH7: 1 | BI7: 1 | BJ7: 0 | BK7: 0 | BL7: 0 | BM7: 1 | BN7: 0 | BO7: 0 | BP7: 0 | BQ7: 1 | BR7: 0 | BS7: 0 | BT7: 0 | BU7: 1 | BV7: 0 | BW7: 0 | BX7: 0 | BY7: 1 | BZ7: 1 | CA7: 1 | CB7: 0 | CC7: 1 | CD7: 1 | CE7: 0 | CF7: 1 | CG7: =SUM(C7:CF7)/82 -> 0.53658537
A8: CE | B8: FUNCAP | C8: 1 | D8: 1 | E8: 1 | F8: 1 | G8: 1 | H8: 0 | I8: 0 | J8: 0 | K8: 1 | L8: 1 | M8: 0 | N8: 1 | O8: 1 | P8: 1 | Q8: 1 | R8: 1 | S8: 1 | T8: 1 | U8: 1 | V8: 1 | W8: 1 | X8: 1 | Y8: 1 | Z8: 1 | AA8: 0 | AB8: 0 | AC8: 0 | AD8: 1 | AE8: 1 | AF8: 0 | AG8: 1 | AH8: 1 | AI8: 1 | AJ8: 1 | AK8: 1 | AL8: 1 | AM8: 1 | AN8: 1 | AO8: 1 | AP8: 1 | AQ8: 1 | AR8: 1 | AS8: 1 | AT8: 0 | AU8: 0 | AV8: 0 | AW8: 1 | AX8: 1 | AY8: 0 | AZ8: 1 | BA8: 1 | BB8: 1 | BC8: 1 | BD8: 1 | BE8: 1 | BF8: 1 | BG8: 1 | BH8: 0 | BI8: 1 | BJ8: 0 | BK8: 0 | BL8: 1 | BM8: 1 | BN8: 0 | BO8: 1 | BP8: 0 | BQ8: 0 | BR8: 0 | BS8: 0 | BT8: 1 | BU8: 1 | BV8: 0 | BW8: 1 | BX8: 0 | BY8: 0 | BZ8: 1 | CA8: 1 | CB8: 0 | CC8: 0 | CD8: 1 | CE8: 0 | CF8: 0 | CG8: =SUM(C8:CF8)/82 -> 0.67073171
A9: DF | B9: FAPDF | C9: 1 | D9: 1 | E9: 1 | F9: 1 | G9: 1 | H9: 0 | I9: 1 | J9: 0 | K9: 0 | L9: 1 | M9: 0 | N9: 1 | O9: 1 | P9: 1 | Q9: 0 | R9: 1 | S9: 1 | T9: 1 | U9: 1 | V9: 1 | W9: 1 | X9: 1 | Y9: 1 | Z9: 1 | AA9: 0 | AB9: 1 | AC9: 0 | AD9: 0 | AE9: 1 | AF9: 0 | AG9: 0 | AH9: 1 | AI9: 1 | AJ9: 0 | AK9: 1 | AL9: 1 | AM9: 1 | AN9: 1 | AO9: 1 | AP9: 1 | AQ9: 1 | AR9: 1 | AS9: 1 | AT9: 0 | AU9: 1 | AV9: 0 | AW9: 0 | AX9: 1 | AY9: 0 | AZ9: 0 | BA9: 1 | BB9: 1 | BC9: 0 | BD9: 1 | BE9: 1 | BF9: 1 | BG9: 1 | BH9: 1 | BI9: 1 | BJ9: 1 | BK9: 1 | BL9: 1 | BM9: 1 | BN9: 1 | BO9: 1 | BP9: 0 | BQ9: 1 | BR9: 1 | BS9: 1 | BT9: 1 | BU9: 1 | BV9: 1 | BW9: 1 | BX9: 0 | BY9: 1 | BZ9: 1 | CA9: 0 | CB9: 1 | CC9: 1 | CD9: 0 | CE9: 0 | CF9: 1 | CG9: =SUM(C9:CF9)/82 -> 0.73170732
A10: ES | B10: FAPES | C10: 1 | D10: 0 | E10: 1 | F10: 0 | G10: 0 | H10: 1 | I10: 0 | J10: 0 | K10: 0 | L10: 0 | M10: 0 | N10: 1 | O10: 0 | P10: 0 | Q10: 1 | R10: 1 | S10: 0 | T10: 0 | U10: 1 | V10: 1 | W10: 1 | X10: 1 | Y10: 1 | Z10: 1 | AA10: 1 | AB10: 1 | AC10: 1 | AD10: 1 | AE10: 1 | AF10: 0 | AG10: 1 | AH10: 0 | AI10: 0 | AJ10: 1 | AK10: 1 | AL10: 0 | AM10: 0 | AN10: 1 | AO10: 1 | AP10: 1 | AQ10: 1 | AR10: 1 | AS10: 1 | AT10: 1 | AU10: 1 | AV10: 1 | AW10: 1 | AX10: 1 | AY10: 0 | AZ10: 1 | BA10: 0 | BB10: 0 | BC10: 1 | BD10: 1 | BE10: 0 | BF10: 0 | BG10: 1 | BH10: 0 | BI10: 1 | BJ10: 0 | BK10: 1 | BL10: 0 | BM10: 1 | BN10: 0 | BO10: 0 | BP10: 1 | BQ10: 0 | BR10: 0 | BS10: 1 | BT10: 0 | BU10: 1 | BV10: 0 | BW10: 0 | BX10: 1 | BY10: 0 | BZ10: 0 | CA10: 0 | CB10: 0 | CC10: 0 | CD10: 1 | CE10: 1 | CF10: 1 | CG10: =SUM(C10:CF10)/82 -> 0.54878049
A11: GO | B11: FAPEG | C11: 1 | D11: 1 | E11: 1 | F11: 1 | G11: 0 | H11: 1 | I11: 0 | J11: 1 | K11: 1 | L11: 0 | M11: 0 | N11: 1 | O11: 0 | P11: 1 | Q11: 0 | R11: 1 | S11: 0 | T11: 0 | U11: 1 | V11: 1 | W11: 0 | X11: 0 | Y11: 1 | Z11: 0 | AA11: 0 | AB11: 0 | AC11: 1 | AD11: 1 | AE11: 1 | AF11: 0 | AG11: 1 | AH11: 0 | AI11: 1 | AJ11: 0 | AK11: 1 | AL11: 0 | AM11: 0 | AN11: 1 | AO11: 1 | AP11: 1 | AQ11: 1 | AR11: 1 | AS11: 1 | AT11: 1 | AU11: 0 | AV11: 1 | AW11: 1 | AX11: 1 | AY11: 0 | AZ11: 1 | BA11: 0 | BB11: 1 | BC11: 0 | BD11: 1 | BE11: 1 | BF11: 0 | BG11: 1 | BH11: 1 | BI11: 0 | BJ11: 1 | BK11: 0 | BL11: 1 | BM11: 0 | BN11: 0 | BO11: 1 | BP11: 1 | BQ11: 1 | BR11: 1 | BS11: 0 | BT11: 1 | BU11: 0 | BV11: 0 | BW11: 1 | BX11: 1 | BY11: 1 | BZ11: 0 | CA11: 1 | CB11: 0 | CC11: 1 | CD11: 0 | CE11: 1 | CF11: 0 | CG11: =SUM(C11:CF11)/82 -> 0.58536585
A12: MA | B12: FAPEMA | C12: 1 | D12: 0 | E12: 0 | F12: 1 | G12: 1 | H12: 0 | I12: 0 | J12: 0 | K12: 1 | L12: 0 | M12: 1 | N12: 0 | O12: 0 | P12: 0 | Q12: 1 | R12: 0 | S12: 0 | T12: 0 | U12: 1 | V12: 1 | W12: 1 | X12: 1 | Y12: 1 | Z12: 1 | AA12: 1 | AB12: 0 | AC12: 0 | AD12: 1 | AE12: 1 | AF12: 1 | AG12: 0 | AH12: 1 | AI12: 0 | AJ12: 1 | AK12: 1 | AL12: 1 | AM12: 1 | AN12: 1 | AO12: 1 | AP12: 1 | AQ12: 1 | AR12: 1 | AS12: 1 | AT12: 1 | AU12: 0 | AV12: 0 | AW12: 1 | AX12: 1 | AY12: 1 | AZ12: 0 | BA12: 1 | BB12: 0 | BC12: 1 | BD12: 1 | BE12: 1 | BF12: 1 | BG12: 1 | BH12: 1 | BI12: 0 | BJ12: 0 | BK12: 1 | BL12: 1 | BM12: 1 | BN12: 0 | BO12: 1 | BP12: 0 | BQ12: 1 | BR12: 0 | BS12: 1 | BT12: 1 | BU12: 1 | BV12: 0 | BW12: 1 | BX12: 0 | BY12: 1 | BZ12: 1 | CA12: 0 | CB12: 0 | CC12: 0 | CD12: 1 | CE12: 1 | CF12: 0 | CG12: =SUM(C12:CF12)/82 -> 0.62195122
A13: MT | B13: FAPEMAT | C13: 1 | D13: 0 | E13: 1 | F13: 0 | G13: 1 | H13: 1 | I13: 0 | J13: 0 | K13: 1 | L13: 1 | M13: 0 | N13: 1 | O13: 1 | P13: 0 | Q13: 0 | R13: 1 | S13: 0 | T13: 1 | U13: 0 | V13: 1 | W13: 1 | X13: 0 | Y13: 0 | Z13: 1 | AA13: 1 | AB13: 0 | AC13: 0 | AD13: 1 | AE13: 1 | AF13: 0 | AG13: 0 | AH13: 1 | AI13: 1 | AJ13: 0 | AK13: 1 | AL13: 1 | AM13: 1 | AN13: 1 | AO13: 0 | AP13: 0 | AQ13: 1 | AR13: 1 | AS13: 1 | AT13: 1 | AU13: 0 | AV13: 0 | AW13: 1 | AX13: 1 | AY13: 0 | AZ13: 1 | BA13: 1 | BB13: 1 | BC13: 0 | BD13: 1 | BE13: 1 | BF13: 1 | BG13: 1 | BH13: 0 | BI13: 1 | BJ13: 1 | BK13: 1 | BL13: 1 | BM13: 0 | BN13: 1 | BO13: 0 | BP13: 0 | BQ13: 0 | BR13: 1 | BS13: 0 | BT13: 1 | BU13: 0 | BV13: 1 | BW13: 0 | BX13: 0 | BY13: 0 | BZ13: 0 | CA13: 1 | CB13: 0 | CC13: 1 | CD13: 0 | CE13: 1 | CF13: 0 | CG13: =SUM(C13:CF13)/82 -> 0.56097561
A14: MS | B14: FUNDECT | C14: 1 | D14: 1 | E14: 1 | F14: 1 | G14: 1 | H14: 1 | I14: 0 | J14: 0 | K14: 0 | L14: 1 | M14: 1 | N14: 1 | O14: 0 | P14: 0 | Q14: 1 | R14: 1 | S14: 0 | T14: 1 | U14: 1 | V14: 1 | W14: 1 | X14: 1 | Y14: 1 | Z14: 1 | AA14: 1 | AB14: 0 | AC14: 0 | AD14: 1 | AE14: 1 | AF14: 1 | AG14: 1 | AH14: 0 | AI14: 0 | AJ14: 1 | AK14: 1 | AL14: 0 | AM14: 1 | AN14: 1 | AO14: 1 | AP14: 1 | AQ14: 1 | AR14: 1 | AS14: 1 | AT14: 1 | AU14: 0 | AV14: 0 | AW14: 0 | AX14: 1 | AY14: 1 | AZ14: 1 | BA14: 0 | BB14: 0 | BC14: 1 | BD14: 1 | BE14: 0 | BF14: 1 | BG14: 1 | BH14: 1 | BI14: 1 | BJ14: 0 | BK14: 1 | BL14: 1 | BM14: 0 | BN14: 1 | BO14: 0 | BP14: 0 | BQ14: 1 | BR14: 0 | BS14: 1 | BT14: 1 | BU14: 0 | BV14: 1 | BW14: 0 | BX14: 0 | BY14: 1 | BZ14: 0 | CA14: 1 | CB14: 1 | CC14: 0 | CD14: 0 | CE14: 1 | CF14: 0 | CG14: =SUM(C14:CF14)/82 -> 0.64634146
... A29: TO | B29: FAPT | C29: 0 | D29: 0 | E29: 0 | F29: 0 | G29: 0 | H29: 0 | I29: 0 | J29: 0 | K29: 1 | L29: 0 | M29: 1 | N29: 1 | O29: 1 | P29: 0 | Q29: 0 | R29: 0 | S29: 0 | T29: 0 | U29: 0 | V29: 0 | W29: 0 | X29: 0 | Y29: 0 | Z29: 0 | AA29: 0 | AB29: 0 | AC29: 0 | AD29: 1 | AE29: 0 | AF29: 1 | AG29: 1 | AH29: 1 | AI29: 0 | AJ29: 0 | AK29: 0 | AL29: 0 | AM29: 0 | AN29: 0 | AO29: 0 | AP29: 0 | AQ29: 0 | AR29: 0 | AS29: 0 | AT29: 0 | AU29: 0 | AV29: 0 | AW29: 1 | AX29: 0 | AY29: 1 | AZ29: 1 | BA29: 1 | BB29: 0 | BC29: 0 | BD29: 0 | BE29: 0 | BF29: 0 | BG29: 0 | BH29: 0 | BI29: 1 | BJ29: 1 | BK29: 1 | BL29: 0 | BM29: 0 | BN29: 0 | BO29: 1 | BP29: 1 | BQ29: 0 | BR29: 1 | BS29: 1 | BT29: 0 | BU29: 0 | BV29: 0 | BW29: 1 | BX29: 1 | BY29: 0 | BZ29: 0 | CA29: 1 | CB29: 0 | CC29: 1 | CD29: 1 | CE29: 0 | CF29: 0 | CG29: =SUM(C29:CF29)/82 -> 0.29268293
B30: Frequencia | C30: =SUM(C3:C29)/27 -> 0.7037037 | D30: =SUM(D3:D29)/27 -> 0.62962963 | E30: =SUM(E3:E29)/27 -> 0.7037037 | F30: =SUM(F3:F29)/27 -> 0.66666667 | G30: =SUM(G3:G29)/27 -> 0.66666667 | H30: =SUM(H3:H29)/27 -> 0.48148148 | I30: =SUM(I3:I29)/27 -> 0.44444444 | J30: =SUM(J3:J29)/27 -> 0.48148148 | ... CF30: =SUM(CF3:CF29)/27 -> 0.44444444 | CG30: =SUM(C30:CF30)/82 -> 0.55058717

Sheet Receitas
A1: Fundação | B1: Transferências Públicas (milhões R$) | C1: Transferências Internacionais (milhões R$) | D1: Receitas Próprias (milhões R$) | E1: Receitas de Pessoas Físicas e Jurídicas (milhões R$) | F1: Outras Receitas (milhões R$)
A2: FAPAC | B2: 30020 | C2: 22610 | D2: 6030 | E2: 5320 | F2: 1150
A3: PAFEAL | B3: 47450 | C3: 4830 | D3: 1360 | E3: 10240 | F3: 750
A4: FAPEAP | B4: 20780 | C4: 25190 | D4: 10360 | E4: 5660 | F4: 3750
A5: FAPEAM | B5: 31950 | C5: 27780 | D5: 4420 | E5: 7190 | F5: 1320
A6: FAPESB | B6: 42620 | C6: 19510 | D6: 12600 | E6: 930 | F6: 4020
A7: FUNCAP | B7: 16210 | C7: 2150 | D7: 13210 | E7: 6410 | F7: 2450
A8: FAPDF | B8: 36100 | C8: 17780 | D8: 3620 | E8: 840 | F8: 3000
A9: FAPES | B9: 35750 | C9: 3470 | D9: 12280 | E9: 11100 | F9: 670
A10: FAPEG | B10: 20220 | C10: 7390 | D10: 17920 | E10: 1530 | F10: 1290
A11: FAPEMA | B11: 44610 | C11: 21700 | D11: 19730 | E11: 4710 | F11: 2540
A12: FAPEMAT | B12: 11410 | C12: 19320 | D12: 6410 | E12: 9710 | F12: 1220
A13: FUNDECT | B13: 7450 | C13: 12020 | D13: 15560 | E13: 5780 | F13: 3340
... A28: FAPT | B28: 40400 | C28: 6760 | D28: 8910 | E28: 8130 | F28: 2310

Sheet Fundações
A1: Fundação | B1: Índice Geral de Tranparência | C1: Estado | D1: Região
A2: ='Dados Geral'!B3 -> FAPAC | B2: ='Dados Geral'!CG3 -> 0.23170732 | C2: ='Dados Geral'!A3 -> AC | D2: Norte
A3: ='Dados Geral'!B4 -> PAFEAL | B3: ='Dados Geral'!CG4 -> 0.67073171 | C3: ='Dados Geral'!A4 -> AL | D3: Nordeste
A4: ='Dados Geral'!B5 -> FAPEAP | B4: ='Dados Geral'!CG5 -> 0.35365854 | C4: ='Dados Geral'!A5 -> AP | D4: Norte
A5: ='Dados Geral'!B6 -> FAPEAM | B5: ='Dados Geral'!CG6 -> 0.25609756 | C5: ='Dados Geral'!A6 -> AM | D5: Norte
A6: ='Dados Geral'!B7 -> FAPESB | B6: ='Dados Geral'!CG7 -> 0.53658537 | C6: ='Dados Geral'!A7 -> BA | D6: Nordeste
A7: ='Dados Geral'!B8 -> FUNCAP | B7: ='Dados Geral'!CG8 -> 0.67073171 | C7: ='Dados Geral'!A8 -> CE | D7: Nordeste
A8: ='Dados Geral'!B9 -> FAPDF | B8: ='Dados Geral'!CG9 -> 0.73170732 | C8: ='Dados Geral'!A9 -> DF | D8: Centro Oeste
A9: ='Dados Geral'!B10 -> FAPES | B9: ='Dados Geral'!CG10 -> 0.54878049 | C9: ='Dados Geral'!A10 -> ES | D9: Sudeste
A10: ='Dados Geral'!B11 -> FAPEG | B10: ='Dados Geral'!CG11 -> 0.58536585 | C10: ='Dados Geral'!A11 -> GO | D10: Centro Oeste
A11: ='Dados Geral'!B12 -> FAPEMA | B11: ='Dados Geral'!CG12 -> 0.62195122 | C11: ='Dados Geral'!A12 -> MA | D11: Nordeste
A12: ='Dados Geral'!B13 -> FAPEMAT | B12: ='Dados Geral'!CG13 -> 0.56097561 | C12: ='Dados Geral'!A13 -> MT | D12: Centro Oeste
A13: ='Dados Geral'!B14 -> FUNDECT | B13: ='Dados Geral'!CG14 -> 0.64634146 | C13: ='Dados Geral'!A14 -> MS | D13: Centro Oeste
... A28: ='Dados Geral'!B29 -> FAPT | B28: ='Dados Geral'!CG29 -> 0.29268293 | C28: ='Dados Geral'!A29 -> TO | D28: Norte
A30: ='Dados Geral'!B31 -> 0
A31: ='Dados Geral'!B32 -> 0

Sheet Regiões
A1: REGIÃO | B1: INDICE GERAL DE DIVULGAÇÃO
A2: Norte | B2: =AVERAGEIF(Fundações!D:D,A2,Fundações!B:B) -> 0.3815331
A3: Nordeste | B3: =AVERAGEIF(Fundações!D:D,A3,Fundações!B:B) -> 0.59620596
A4: Centro Oeste | B4: =AVERAGEIF(Fundações!D:D,A4,Fundações!B:B) -> 0.63109756
A5: Sudeste | B5: =AVERAGEIF(Fundações!D:D,A5,Fundações!B:B) -> 0.61585366
A6: Sul | B6: =AVERAGEIF(Fundações!D:D,A6,Fundações!B:B) -> 0.61382114

Sheet D1
A1: ='Dados Geral'!B2 -> FUNDAÇÃO | B1: ='Dados Geral'!C2 -> Informa claramente sobre o seu ramo de atividade | C1: ='Dados Geral'!D2 -> Indica inequivocamente quem são os beneficiários das suas operações | D1: ='Dados Geral'!E2 -> A missão da organização está claramente definida | E1: ='Dados Geral'!F2 -> A visão da organização está claramente definida | F1: ='Dados Geral'!G2 -> Os valores estão enunciados e a interpretação que a organização faz deles são definidos | G1: ='Dados Geral'!H2 -> Informações sobre os interesses que representa (da ciência e tecnologia, de ensino, pesquisa e extensão) | H1: ='Dados Geral'!I2 -> Os objetivos da organização são claros, precisos e passíveis de avaliação | ... T1: ='Dados Geral'!U2 -> Informações sobre vínculos com financiadores, associações ou empresas
A2: ='Dados Geral'!B3 -> FAPAC | B2: ='Dados Geral'!C3 -> 0 | C2: ='Dados Geral'!D3 -> 0 | D2: ='Dados Geral'!E3 -> 0 | E2: ='Dados Geral'!F3 -> 0 | F2: ='Dados Geral'!G3 -> 0 | G2: ='Dados Geral'!H3 -> 1 | H2: ='Dados Geral'!I3 -> 0 | ... T2: ='Dados Geral'!U3 -> 0
A3: ='Dados Geral'!B4 -> PAFEAL | B3: ='Dados Geral'!C4 -> 1 | C3: ='Dados Geral'!D4 -> 1 | D3: ='Dados Geral'!E4 -> 1 | E3: ='Dados Geral'!F4 -> 1 | F3: ='Dados Geral'!G4 -> 1 | G3: ='Dados Geral'!H4 -> 0 | H3: ='Dados Geral'!I4 -> 1 | ... T3: ='Dados Geral'!U4 -> 1
A4: ='Dados Geral'!B5 -> FAPEAP | B4: ='Dados Geral'!C5 -> 0 | C4: ='Dados Geral'!D5 -> 0 | D4: ='Dados Geral'!E5 -> 0 | E4: ='Dados Geral'!F5 -> 0 | F4: ='Dados Geral'!G5 -> 0 | G4: ='Dados Geral'!H5 -> 0 | H4: ='Dados Geral'!I5 -> 0 | ... T4: ='Dados Geral'!U5 -> 0
A5: ='Dados Geral'!B6 -> FAPEAM | B5: ='Dados Geral'!C6 -> 0 | C5: ='Dados Geral'!D6 -> 0 | D5: ='Dados Geral'!E6 -> 0 | E5: ='Dados Geral'!F6 -> 0 | F5: ='Dados Geral'!G6 -> 0 | G5: ='Dados Geral'!H6 -> 1 | H5: ='Dados Geral'!I6 -> 0 | ... T5: ='Dados Geral'!U6 -> 0
A6: ='Dados Geral'!B7 -> FAPESB | B6: ='Dados Geral'!C7 -> 1 | C6: ='Dados Geral'!D7 -> 1 | D6: ='Dados Geral'!E7 -> 1 | E6: ='Dados Geral'!F7 -> 1 | F6: ='Dados Geral'!G7 -> 1 | G6: ='Dados Geral'!H7 -> 0 | H6: ='Dados Geral'!I7 -> 1 | ... T6: ='Dados Geral'!U7 -> 1
A7: ='Dados Geral'!B8 -> FUNCAP | B7: ='Dados Geral'!C8 -> 1 | C7: ='Dados Geral'!D8 -> 1 | D7: ='Dados Geral'!E8 -> 1 | E7: ='Dados Geral'!F8 -> 1 | F7: ='Dados Geral'!G8 -> 1 | G7: ='Dados Geral'!H8 -> 0 | H7: ='Dados Geral'!I8 -> 0 | ... T7: ='Dados Geral'!U8 -> 1
A8: ='Dados Geral'!B9 -> FAPDF | B8: ='Dados Geral'!C9 -> 1 | C8: ='Dados Geral'!D9 -> 1 | D8: ='Dados Geral'!E9 -> 1 | E8: ='Dados Geral'!F9 -> 1 | F8: ='Dados Geral'!G9 -> 1 | G8: ='Dados Geral'!H9 -> 0 | H8: ='Dados Geral'!I9 -> 1 | ... T8: ='Dados Geral'!U9 -> 1
A9: ='Dados Geral'!B10 -> FAPES | B9: ='Dados Geral'!C10 -> 1 | C9: ='Dados Geral'!D10 -> 0 | D9: ='Dados Geral'!E10 -> 1 | E9: ='Dados Geral'!F10 -> 0 | F9: ='Dados Geral'!G10 -> 0 | G9: ='Dados Geral'!H10 -> 1 | H9: ='Dados Geral'!I10 -> 0 | ... T9: ='Dados Geral'!U10 -> 1
A10: ='Dados Geral'!B11 -> FAPEG | B10: ='Dados Geral'!C11 -> 1 | C10: ='Dados Geral'!D11 -> 1 | D10: ='Dados Geral'!E11 -> 1 | E10: ='Dados Geral'!F11 -> 1 | F10: ='Dados Geral'!G11 -> 0 | G10: ='Dados Geral'!H11 -> 1 | H10: ='Dados Geral'!I11 -> 0 | ... T10: ='Dados Geral'!U11 -> 1
A11: ='Dados Geral'!B12 -> FAPEMA | B11: ='Dados Geral'!C12 -> 1 | C11: ='Dados Geral'!D12 -> 0 | D11: ='Dados Geral'!E12 -> 0 | E11: ='Dados Geral'!F12 -> 1 | F11: ='Dados Geral'!G12 -> 1 | G11: ='Dados Geral'!H12 -> 0 | H11: ='Dados Geral'!I12 -> 0 | ... T11: ='Dados Geral'!U12 -> 1
A12: ='Dados Geral'!B13 -> FAPEMAT | B12: ='Dados Geral'!C13 -> 1 | C12: ='Dados Geral'!D13 -> 0 | D12: ='Dados Geral'!E13 -> 1 | E12: ='Dados Geral'!F13 -> 0 | F12: ='Dados Geral'!G13 -> 1 | G12: ='Dados Geral'!H13 -> 1 | H12: ='Dados Geral'!I13 -> 0 | ... T12: ='Dados Geral'!U13 -> 0
... A28: ='Dados Geral'!B29 -> FAPT | B28: ='Dados Geral'!C29 -> 0 | C28: ='Dados Geral'!D29 -> 0 | D28: ='Dados Geral'!E29 -> 0 | E28: ='Dados Geral'!F29 -> 0 | F28: ='Dados Geral'!G29 -> 0 | G28: ='Dados Geral'!H29 -> 0 | H28: ='Dados Geral'!I29 -> 0 | ... T28: ='Dados Geral'!U29 -> 0

Sheet D2
A1: ='Dados Geral'!B2 -> FUNDAÇÃO | B1: ='Dados Geral'!V2 -> Nomes e histórico sucinto de todos os membros dos conselhos diretivos e de administração | C1: ='Dados Geral'!W2 -> Calendário de reuniões | D1: ='Dados Geral'!X2 -> Estatutos, regulamentos ou regimes internos de funcionamento | E1: ='Dados Geral'!Y2 -> Divulga os acordos adotados nas reuniões convocadas | F1: ='Dados Geral'!Z2 -> Informa sobre os procedimentos de eleição e destituição de membros do conselho de administração curadores | G1: ='Dados Geral'!AA2 -> Informa sobre a política de remuneração dos componentes do conselho diretivo e de administração | H1: ='Dados Geral'!AB2 -> Eixo estratégico do orçamento | I1: ='Dados Geral'!AC2 -> Orçamento distribuído por programas, projetos e convênios | ... AG1: ='Dados Geral'!BA2 -> Cópia dos contratos, termos e convênios firmados
A2: ='Dados Geral'!B3 -> FAPAC | B2: ='Dados Geral'!V3 -> 0 | C2: ='Dados Geral'!W3 -> 0 | D2: ='Dados Geral'!X3 -> 0 | E2: ='Dados Geral'!Y3 -> 0 | F2: ='Dados Geral'!Z3 -> 0 | G2: ='Dados Geral'!AA3 -> 1 | H2: ='Dados Geral'!AB3 -> 0 | I2: ='Dados Geral'!AC3 -> 0 | ... AG2: ='Dados Geral'!BA3 -> 0
A3: ='Dados Geral'!B4 -> PAFEAL | B3: ='Dados Geral'!V4 -> 1 | C3: ='Dados Geral'!W4 -> 1 | D3: ='Dados Geral'!X4 -> 1 | E3: ='Dados Geral'!Y4 -> 1 | F3: ='Dados Geral'!Z4 -> 1 | G3: ='Dados Geral'!AA4 -> 0 | H3: ='Dados Geral'!AB4 -> 1 | I3: ='Dados Geral'!AC4 -> 1 | ... AG3: ='Dados Geral'!BA4 -> 1
A4: ='Dados Geral'!B5 -> FAPEAP | B4: ='Dados Geral'!V5 -> 0 | C4: ='Dados Geral'!W5 -> 0 | D4: ='Dados Geral'!X5 -> 0 | E4: ='Dados Geral'!Y5 -> 0 | F4: ='Dados Geral'!Z5 -> 0 | G4: ='Dados Geral'!AA5 -> 0 | H4: ='Dados Geral'!AB5 -> 0 | I4: ='Dados Geral'!AC5 -> 1 | ... AG4: ='Dados Geral'!BA5 -> 1
A5: ='Dados Geral'!B6 -> FAPEAM | B5: ='Dados Geral'!V6 -> 0 | C5: ='Dados Geral'!W6 -> 0 | D5: ='Dados Geral'!X6 -> 0 | E5: ='Dados Geral'!Y6 -> 0 | F5: ='Dados Geral'!Z6 -> 0 | G5: ='Dados Geral'!AA6 -> 1 | H5: ='Dados Geral'!AB6 -> 0 | I5: ='Dados Geral'!AC6 -> 0 | ... AG5: ='Dados Geral'!BA6 -> 1
A6: ='Dados Geral'!B7 -> FAPESB | B6: ='Dados Geral'!V7 -> 1 | C6: ='Dados Geral'!W7 -> 1 | D6: ='Dados Geral'!X7 -> 1 | E6: ='Dados Geral'!Y7 -> 1 | F6: ='Dados Geral'!Z7 -> 1 | G6: ='Dados Geral'!AA7 -> 0 | H6: ='Dados Geral'!AB7 -> 1 | I6: ='Dados Geral'!AC7 -> 0 | ... AG6: ='Dados Geral'!BA7 -> 0
A7: ='Dados Geral'!B8 -> FUNCAP | B7: ='Dados Geral'!V8 -> 1 | C7: ='Dados Geral'!W8 -> 1 | D7: ='Dados Geral'!X8 -> 1 | E7: ='Dados Geral'!Y8 -> 1 | F7: ='Dados Geral'!Z8 -> 1 | G7: ='Dados Geral'!AA8 -> 0 | H7: ='Dados Geral'!AB8 -> 0 | I7: ='Dados Geral'!AC8 -> 0 | ... AG7: ='Dados Geral'!BA8 -> 1
A8: ='Dados Geral'!B9 -> FAPDF | B8: ='Dados Geral'!V9 -> 1 | C8: ='Dados Geral'!W9 -> 1 | D8: ='Dados Geral'!X9 -> 1 | E8: ='Dados Geral'!Y9 -> 1 | F8: ='Dados Geral'!Z9 -> 1 | G8: ='Dados Geral'!AA9 -> 0 | H8: ='Dados Geral'!AB9 -> 1 | I8: ='Dados Geral'!AC9 -> 0 | ... AG8: ='Dados Geral'!BA9 -> 1
A9: ='Dados Geral'!B10 -> FAPES | B9: ='Dados Geral'!V10 -> 1 | C9: ='Dados Geral'!W10 -> 1 | D9: ='Dados Geral'!X10 -> 1 | E9: ='Dados Geral'!Y10 -> 1 | F9: ='Dados Geral'!Z10 -> 1 | G9: ='Dados Geral'!AA10 -> 1 | H9: ='Dados Geral'!AB10 -> 1 | I9: ='Dados Geral'!AC10 -> 1 | ... AG9: ='Dados Geral'!BA10 -> 0
A10: ='Dados Geral'!B11 -> FAPEG | B10: ='Dados Geral'!V11 -> 1 | C10: ='Dados Geral'!W11 -> 0 | D10: ='Dados Geral'!X11 -> 0 | E10: ='Dados Geral'!Y11 -> 1 | F10: ='Dados Geral'!Z11 -> 0 | G10: ='Dados Geral'!AA11 -> 0 | H10: ='Dados Geral'!AB11 -> 0 | I10: ='Dados Geral'!AC11 -> 1 | ... AG10: ='Dados Geral'!BA11 -> 0
A11: ='Dados Geral'!B12 -> FAPEMA | B11: ='Dados Geral'!V12 -> 1 | C11: ='Dados Geral'!W12 -> 1 | D11: ='Dados Geral'!X12 -> 1 | E11: ='Dados Geral'!Y12 -> 1 | F11: ='Dados Geral'!Z12 -> 1 | G11: ='Dados Geral'!AA12 -> 1 | H11: ='Dados Geral'!AB12 -> 0 | I11: ='Dados Geral'!AC12 -> 0 | ... AG11: ='Dados Geral'!BA12 -> 1
A12: ='Dados Geral'!B13 -> FAPEMAT | B12: ='Dados Geral'!V13 -> 1 | C12: ='Dados Geral'!W13 -> 1 | D12: ='Dados Geral'!X13 -> 0 | E12: ='Dados Geral'!Y13 -> 0 | F12: ='Dados Geral'!Z13 -> 1 | G12: ='Dados Geral'!AA13 -> 1 | H12: ='Dados Geral'!AB13 -> 0 | I12: ='Dados Geral'!AC13 -> 0 | ... AG12: ='Dados Geral'!BA13 -> 1
... A28: ='Dados Geral'!B29 -> FAPT | B28: ='Dados Geral'!V29 -> 0 | C28: ='Dados Geral'!W29 -> 0 | D28: ='Dados Geral'!X29 -> 0 | E28: ='Dados Geral'!Y29 -> 0 | F28: ='Dados Geral'!Z29 -> 0 | G28: ='Dados Geral'!AA29 -> 0 | H28: ='Dados Geral'!AB29 -> 0 | I28: ='Dados Geral'!AC29 -> 0 | ... AG28: ='Dados Geral'!BA29 -> 1

Sheet D3
A1: ='Dados Geral'!B2 -> FUNDAÇÃO | B1: ='Dados Geral'!BB2 -> Há uma área específica para governança e informações financeiras | C1: ='Dados Geral'!BC2 -> Há uma área específica para informações gerais | D1: ='Dados Geral'!BD2 -> Há links para outros sites relacionados | E1: ='Dados Geral'!BE2 -> Um endereço de e-mail para contato é fornecido | F1: ='Dados Geral'!BF2 -> O conteúdo é apresentado em um maneira estruturada e alinhada e pode ser acessado rápida e diretamente | G1: ='Dados Geral'!BG2 -> Os títulos são claros e significativos e a linguagem utilizada é adaptada aos cidadãos | H1: ='Dados Geral'!BH2 -> Divulgação de fotografias das atividades desenvolvidas pela organização | I1: ='Dados Geral'!BI2 -> Divulgação de vídeos das atividades realizadas pela organização | ... AF1: ='Dados Geral'!CF2 -> Os parceiros têm um espaço de acesso exclusivo que lhes permite realizar atividades administrativas: obter certificados de doações, atualizar seus dados, fazer contribuições, etc.
A2: ='Dados Geral'!B3 -> FAPAC | B2: ='Dados Geral'!BB3 -> 0 | C2: ='Dados Geral'!BC3 -> 1 | D2: ='Dados Geral'!BD3 -> 0 | E2: ='Dados Geral'!BE3 -> 0 | F2: ='Dados Geral'!BF3 -> 1 | G2: ='Dados Geral'!BG3 -> 0 | H2: ='Dados Geral'!BH3 -> 0 | I2: ='Dados Geral'!BI3 -> 0 | ... AF2: ='Dados Geral'!CF3 -> 0
A3: ='Dados Geral'!B4 -> PAFEAL | B3: ='Dados Geral'!BB4 -> 0 | C3: ='Dados Geral'!BC4 -> 1 | D3: ='Dados Geral'!BD4 -> 1 | E3: ='Dados Geral'!BE4 -> 0 | F3: ='Dados Geral'!BF4 -> 1 | G3: ='Dados Geral'!BG4 -> 1 | H3: ='Dados Geral'!BH4 -> 0 | I3: ='Dados Geral'!BI4 -> 1 | ... AF3: ='Dados Geral'!CF4 -> 1
A4: ='Dados Geral'!B5 -> FAPEAP | B4: ='Dados Geral'!BB5 -> 0 | C4: ='Dados Geral'!BC5 -> 0 | D4: ='Dados Geral'!BD5 -> 0 | E4: ='Dados Geral'!BE5 -> 0 | F4: ='Dados Geral'!BF5 -> 0 | G4: ='Dados Geral'!BG5 -> 0 | H4: ='Dados Geral'!BH5 -> 1 | I4: ='Dados Geral'!BI5 -> 0 | ... AF4: ='Dados Geral'!CF5 -> 0
A5: ='Dados Geral'!B6 -> FAPEAM | B5: ='Dados Geral'!BB6 -> 0 | C5: ='Dados Geral'!BC6 -> 0 | D5: ='Dados Geral'!BD6 -> 0 | E5: ='Dados Geral'!BE6 -> 0 | F5: ='Dados Geral'!BF6 -> 0 | G5: ='Dados Geral'!BG6 -> 0 | H5: ='Dados Geral'!BH6 -> 1 | I5: ='Dados Geral'!BI6 -> 1 | ... AF5: ='Dados Geral'!CF6 -> 0
A6: ='Dados Geral'!B7 -> FAPESB | B6: ='Dados Geral'!BB7 -> 0 | C6: ='Dados Geral'!BC7 -> 1 | D6: ='Dados Geral'!BD7 -> 1 | E6: ='Dados Geral'!BE7 -> 1 | F6: ='Dados Geral'!BF7 -> 0 | G6: ='Dados Geral'!BG7 -> 1 | H6: ='Dados Geral'!BH7 -> 1 | I6: ='Dados Geral'!BI7 -> 1 | ... AF6: ='Dados Geral'!CF7 -> 1
A7: ='Dados Geral'!B8 -> FUNCAP | B7: ='Dados Geral'!BB8 -> 1 | C7: ='Dados Geral'!BC8 -> 1 | D7: ='Dados Geral'!BD8 -> 1 | E7: ='Dados Geral'!BE8 -> 1 | F7: ='Dados Geral'!BF8 -> 1 | G7: ='Dados Geral'!BG8 -> 1 | H7: ='Dados Geral'!BH8 -> 0 | I7: ='Dados Geral'!BI8 -> 1 | ... AF7: ='Dados Geral'!CF8 -> 0
A8: ='Dados Geral'!B9 -> FAPDF | B8: ='Dados Geral'!BB9 -> 1 | C8: ='Dados Geral'!BC9 -> 0 | D8: ='Dados Geral'!BD9 -> 1 | E8: ='Dados Geral'!BE9 -> 1 | F8: ='Dados Geral'!BF9 -> 1 | G8: ='Dados Geral'!BG9 -> 1 | H8: ='Dados Geral'!BH9 -> 1 | I8: ='Dados Geral'!BI9 -> 1 | ... AF8: ='Dados Geral'!CF9 -> 1
A9: ='Dados Geral'!B10 -> FAPES | B9: ='Dados Geral'!BB10 -> 0 | C9: ='Dados Geral'!BC10 -> 1 | D9: ='Dados Geral'!BD10 -> 1 | E9: ='Dados Geral'!BE10 -> 0 | F9: ='Dados Geral'!BF10 -> 0 | G9: ='Dados Geral'!BG10 -> 1 | H9: ='Dados Geral'!BH10 -> 0 | I9: ='Dados Geral'!BI10 -> 1 | ... AF9: ='Dados Geral'!CF10 -> 1
A10: ='Dados Geral'!B11 -> FAPEG | B10: ='Dados Geral'!BB11 -> 1 | C10: ='Dados Geral'!BC11 -> 0 | D10: ='Dados Geral'!BD11 -> 1 | E10: ='Dados Geral'!BE11 -> 1 | F10: ='Dados Geral'!BF11 -> 0 | G10: ='Dados Geral'!BG11 -> 1 | H10: ='Dados Geral'!BH11 -> 1 | I10: ='Dados Geral'!BI11 -> 0 | ... AF10: ='Dados Geral'!CF11 -> 0
A11: ='Dados Geral'!B12 -> FAPEMA | B11: ='Dados Geral'!BB12 -> 0 | C11: ='Dados Geral'!BC12 -> 1 | D11: ='Dados Geral'!BD12 -> 1 | E11: ='Dados Geral'!BE12 -> 1 | F11: ='Dados Geral'!BF12 -> 1 | G11: ='Dados Geral'!BG12 -> 1 | H11: ='Dados Geral'!BH12 -> 1 | I11: ='Dados Geral'!BI12 -> 0 | ... AF11: ='Dados Geral'!CF12 -> 0
A12: ='Dados Geral'!B13 -> FAPEMAT | B12: ='Dados Geral'!BB13 -> 1 | C12: ='Dados Geral'!BC13 -> 0 | D12: ='Dados Geral'!BD13 -> 1 | E12: ='Dados Geral'!BE13 -> 1 | F12: ='Dados Geral'!BF13 -> 1 | G12: ='Dados Geral'!BG13 -> 1 | H12: ='Dados Geral'!BH13 -> 0 | I12: ='Dados Geral'!BI13 -> 1 | ... AF12: ='Dados Geral'!CF13 -> 0
... A28: ='Dados Geral'!B29 -> FAPT | B28: ='Dados Geral'!BB29 -> 0 | C28: ='Dados Geral'!BC29 -> 0 | D28: ='Dados Geral'!BD29 -> 0 | E28: ='Dados Geral'!BE29 -> 0 | F28: ='Dados Geral'!BF29 -> 0 | G28: ='Dados Geral'!BG29 -> 0 | H28: ='Dados Geral'!BH29 -> 0 | I28: ='Dados Geral'!BI29 -> 1 | ... AF28: ='Dados Geral'!CF29 -> 0
